Covalent/Balances.py
Covalent/NFT.py
Covalent/Transactions.py
Covalent/__init__.py
Covalent/helper.py
Zora/__init__.py
Zora/agg_att.py
Zora/agg_stats.py
Zora/collections_metadata.py
Zora/events.py
Zora/helper.py
Zora/mints.py
Zora/off_chain.py
Zora/sales.py
Zora/search.py
Zora/tokens.py
Zora/url.py
mode/__init__.py
mode/helper.py
mode/testnet.py
Web3toolkit-1.0.7.dist-info/METADATA
Web3toolkit-1.0.7.dist-info/WHEEL
Web3toolkit-1.0.7.dist-info/top_level.txt
Web3toolkit-1.0.7.dist-info/RECORD
